djangocms_thumbnail_slider/__init__.py
djangocms_thumbnail_slider/admin.py
djangocms_thumbnail_slider/cms_plugins.py
djangocms_thumbnail_slider/forms.py
djangocms_thumbnail_slider/models.py
djangocms_thumbnail_slider/tests.py
djangocms_thumbnail_slider/views.py
djangocms_thumbnail_slider-1.0.0.dist-info/DESCRIPTION.rst
djangocms_thumbnail_slider-1.0.0.dist-info/METADATA
djangocms_thumbnail_slider-1.0.0.dist-info/RECORD
djangocms_thumbnail_slider-1.0.0.dist-info/WHEEL
djangocms_thumbnail_slider-1.0.0.dist-info/metadata.json
djangocms_thumbnail_slider-1.0.0.dist-info/top_level.txt
