Metadata-Version: 2.0
Name: djangocms-thumbnail-slider
Version: 1.0.0
Summary: Thumbnail slider plugin for Django CMS
Home-page: https://github.com/Logicify/djangocms-thumbnail-slider
Author: Dmitriy Selischev
Author-email: dmitriy.selischev@logicify.com
License: MIT
Keywords: django cms plugin thumbnail slider image
Platform: UNKNOWN
Classifier: Development Status :: 3 - Alpha
Classifier: Intended Audience :: Developers
Classifier: Topic :: Software Development :: Build Tools
Classifier: License :: OSI Approved :: MIT License
Classifier: Programming Language :: Python :: 3
Classifier: Programming Language :: Python :: 3.5
Classifier: Programming Language :: Python :: 3.6
Requires-Dist: django
Requires-Dist: django-cms
Requires-Dist: cmsplugin-filer
Requires-Dist: django-sekizai
Provides-Extra: dev
Provides-Extra: test
